torchlaunch/__init__.py
torchlaunch/demo_train.py
torchlaunch/launcher.py
torchlaunch/requirements.txt
torchlaunch-0.1.1.dist-info/METADATA
torchlaunch-0.1.1.dist-info/WHEEL
torchlaunch-0.1.1.dist-info/licenses/LICENSE
torchlaunch-0.1.1.dist-info/RECORD
