Metadata-Version: 2.4
Name: torchlaunch
Version: 0.1.1
Summary: Zero-boilerplate distributed-training launcher for PyTorch
Project-URL: Homepage, https://github.com/levoz92/torchlaunch
Project-URL: Issues, https://github.com/levoz92/torchlaunch/issues
Author-email: Levent Ozbek <levent.ozbek.92@gmail.com>
License: MIT
License-File: LICENSE
Requires-Python: >=3.8
Requires-Dist: filelock~=3.18
Requires-Dist: torch>=2.6
Provides-Extra: dev
Requires-Dist: fsspec~=2025.3; extra == 'dev'
Requires-Dist: jinja2~=3.1; extra == 'dev'
Requires-Dist: networkx~=3.4; extra == 'dev'
Requires-Dist: numpy~=2.2; extra == 'dev'
Requires-Dist: pandas~=2.2; extra == 'dev'
Requires-Dist: pynvml; (platform_system == 'Linux' or platform_system == 'Windows') and extra == 'dev'
Requires-Dist: pytest>=8.0; extra == 'dev'
Requires-Dist: python-dateutil~=2.9; extra == 'dev'
Requires-Dist: pytz~=2025.2; extra == 'dev'
Requires-Dist: ruff>=0.4; extra == 'dev'
Requires-Dist: sympy~=1.13; extra == 'dev'
Requires-Dist: typing-extensions~=4.13; extra == 'dev'
Requires-Dist: tzdata~=2025.2; extra == 'dev'
Provides-Extra: full
Requires-Dist: fsspec~=2025.3; extra == 'full'
Requires-Dist: jinja2~=3.1; extra == 'full'
Requires-Dist: networkx~=3.4; extra == 'full'
Requires-Dist: numpy~=2.2; extra == 'full'
Requires-Dist: pandas~=2.2; extra == 'full'
Requires-Dist: pynvml; (platform_system == 'Linux' or platform_system == 'Windows') and extra == 'full'
Requires-Dist: python-dateutil~=2.9; extra == 'full'
Requires-Dist: pytz~=2025.2; extra == 'full'
Requires-Dist: sympy~=1.13; extra == 'full'
Requires-Dist: typing-extensions~=4.13; extra == 'full'
Requires-Dist: tzdata~=2025.2; extra == 'full'
